batchdim/__init__.py
batch_dimension-0.1.0.dist-info/METADATA
batch_dimension-0.1.0.dist-info/WHEEL
batch_dimension-0.1.0.dist-info/licenses/LICENSE
batch_dimension-0.1.0.dist-info/RECORD
